ref/__init__.py
restricted_functions-1.2.3.dist-info/LICENSE
restricted_functions-1.2.3.dist-info/METADATA
restricted_functions-1.2.3.dist-info/WHEEL
restricted_functions-1.2.3.dist-info/top_level.txt
restricted_functions-1.2.3.dist-info/RECORD
