Metadata-Version: 2.1
Name: restricted-functions
Version: 1.2.3
Summary: Restricted-functions is a package for Python that allows you to deny dangerous functions.
Home-page: http://restricted-functions.tk/
Author: Elisha Hollander, Alexander Bina
License: MIT
Project-URL: Documentation, https://github.com/donno2048/restricted-functions#readme
Project-URL: Bug Reports, https://github.com/donno2048/restricted-functions/issues
Project-URL: Source Code, https://github.com/donno2048/restricted-functions
Platform: UNKNOWN
Classifier: Development Status :: 6 - Mature
Classifier: Environment :: No Input/Output (Daemon)
Classifier: Intended Audience :: Developers
Classifier: License :: OSI Approved :: MIT License
Classifier: Natural Language :: English
Classifier: Operating System :: OS Independent
Classifier: Programming Language :: Python :: 3 :: Only
Classifier: Topic :: Security
Requires-Python: >=3.0
